golden_record_exe/__init__.py
golden_record_exe/__main__.py
golden_record_T1-0.1.0.dist-info/METADATA
golden_record_T1-0.1.0.dist-info/WHEEL
golden_record_T1-0.1.0.dist-info/top_level.txt
golden_record_T1-0.1.0.dist-info/RECORD
