Metadata-Version: 2.1
Name: golden_record_T1
Version: 0.1.0
Summary: Пакет, анализирующий датасет и возвращающий её "Золотую запись".
Author-email: Pablo_3_16 <p.ergle@edu.centraluniversity.ru>
Requires-Python: >=3.12
Requires-Dist: pandas>=2.2.3
Requires-Dist: dask>=2024.11.2
Requires-Dist: dask-expr>=1.1.19
